httpx_mcp/__init__.py
httpx_mcp/server.py
httpx_mcp-1.0.0.dist-info/METADATA
httpx_mcp-1.0.0.dist-info/WHEEL
httpx_mcp-1.0.0.dist-info/entry_points.txt
httpx_mcp-1.0.0.dist-info/RECORD
