Metadata-Version: 2.4
Name: httpx-mcp
Version: 1.0.0
Summary: A MCP tool for HTTP request testing using httpx
Author-email: ZHEFOX <zhefox@outlook.com>
Requires-Python: >=3.10
Requires-Dist: httpx>=0.27.0
Requires-Dist: mcp>=1.0.0
